setup.py
gaussnomial/Binomialdistribution.py
gaussnomial/Gaussiandistribution.py
gaussnomial/Generaldistribution.py
gaussnomial/__init__.py
gaussnomial.egg-info/PKG-INFO
gaussnomial.egg-info/SOURCES.txt
gaussnomial.egg-info/dependency_links.txt
gaussnomial.egg-info/not-zip-safe
gaussnomial.egg-info/top_level.txt