Metadata-Version: 1.0
Name: gaussnomial
Version: 0.1
Summary: Gaussian distributions
Home-page: UNKNOWN
Author: shashi kumar soni
Author-email: skssunny30@gmail.com
License: UNKNOWN
Platform: UNKNOWN
